petro_res_pack/__init__.py
petro_res_pack/math_phis_utils.py
petro_res_pack/parsing_utils.py
petro_res_pack/petro_env.py
petro_res_pack/petro_session.py
petro_res_pack/petro_wrappers.py
petro_res_pack/properties.py
petro_res_pack/res_state.py
petro_res_pack/sub_matices_utils.py
petro_res_pack/sub_matrices_utils.py
petro_res_pack/utils.py
petro_res_pack-0.8.2.dist-info/METADATA
petro_res_pack-0.8.2.dist-info/WHEEL
petro_res_pack-0.8.2.dist-info/top_level.txt
petro_res_pack-0.8.2.dist-info/RECORD
