Metadata-Version: 2.1
Name: petro-res-pack
Version: 0.8.2
Summary: Package with gym-like env for petroleum reservoir simulation
Home-page: https://github.com/lemikhovalex/ReservoirModel
Author: Aleksandr Lemikhov
Author-email: lemikhovalex@gmail.com
License: MIT
Platform: UNKNOWN
